excore/__init__.py
excore/config.py
excore/constants.py
excore/exceptions.py
excore/hooks.py
excore/hub.py
excore/logger.py
excore/registry.py
excore-0.1.1.dist-info/METADATA
excore-0.1.1.dist-info/WHEEL
excore-0.1.1.dist-info/RECORD
